{"qC+nwSXk8MC3IxTQ8fpyGA==":"logosolo-175x175.png","X/ojlMup247KQ/q0wcHfkg==":"hero-bg-1600x800.jpg","DBNck/iwc4r5jqF0SLMgGg==":"bricks-166919-1920-1920x1410.jpg","cnQwpeSG8GhZfrPOkhBTzw==":"hero-bg-1-1600x800.jpg","6K6ncmwX45GqNU2qH32qaQ==":"logover-413x502.png","qNKYVbR2FBnVh1K/+Hoq5w==":"plants-bg-1600x1067.jpg","0UGlemP7FnBfvMT2HeKtaA==":"portfolio-1-720x400.jpg","XxJ+pT/q2pqVjqLDeRIe8g==":"portfolio-2-720x400.jpg","JdzXhljcJAFAZtq9XGPdZw==":"portfolio-3-720x400.jpg","UTgH71ce4FC8YKUM/gWDDQ==":"keyboard-bg-1600x1200.jpg","Fn4k0waVkqzsZcZ113Fctw==":"keyboard-bg-1-1600x1200.jpg","wRZwKNn7jH8w9QKukMwGNw==":"guillermo-4000x6000.png","sW2tkF+L5r0fESzU28a5+w==":"elizabeth-6000x4000.png","Kr/Z8lGeTcbOH77n+TCtGA==":"elizabeth-1-6000x4000.png","Lw5iCCzCh5+ZJmILi+xWIw==":"catalina-6000x4000.png","j9EXJFcW/OyuAnOpioGA9A==":"sala-1059x388.png","i/bpWd/XRk7FYWz+vOdfnw==":"leopoldo-6000x4000.png","CynMlUs5zewZQ7Ry8R7BdQ==":"logosolo-175x175.jpg","pZAC1SwN6u5QIEYXbGdFsA==":"logosolo-1-175x175.jpg","dNRITNAV9YV3slIsO3Uosw==":"logosolo-2-175x175.jpg","CTikLXbYg1PBX3lTUVHKiw==":"connnie-842x1051.jpg","5nAZptX7sJuTxLVrt+IAjQ==":"connnie-1-842x1051.jpg"}